[{"Id":2,"Jugador1":{"Id":12,"Puntaje":56,"Nombre":"Pedro","Victorias":0,"Turnos":5,"ListaCategorias":[{"1":true,"2":true,"3":true,"4":false,"5":true,"6":false,"Es Poker":true}]},"Jugador2":{"Id":13,"Puntaje":22,"Nombre":"Raul","Victorias":0,"Turnos":5,"ListaCategorias":[{"1":true,"2":true,"3":true,"4":true,"5":true,"6":false}]},"NombreJugadorGanador":"Pedro"},{"Id":2,"Jugador1":{"Id":12,"Puntaje":56,"Nombre":"Pedro","Victorias":0,"Turnos":5,"ListaCategorias":[{"1":true,"2":true,"3":true,"4":false,"5":true,"6":false,"Es Poker":true}]},"Jugador2":{"Id":13,"Puntaje":22,"Nombre":"Raul","Victorias":0,"Turnos":5,"ListaCategorias":[{"1":true,"2":true,"3":true,"4":true,"5":true,"6":false}]},"NombreJugadorGanador":"Pedro"},{"Id":1,"Jugador1":{"Id":13,"Puntaje":58,"Nombre":"Raul","Victorias":0,"Turnos":5,"ListaCategorias":[{"1":true,"2":true,"3":true,"4":true,"5":false,"6":true}]},"Jugador2":{"Id":14,"Puntaje":35,"Nombre":"Kevin","Victorias":0,"Turnos":5,"ListaCategorias":[{"1":true,"2":true,"3":true,"4":false,"5":true,"6":true}]},"NombreJugadorGanador":"Raul"}]